<?xml version='1.0' encoding='ISO-8859-1' ?>
<!DOCTYPE toc
  PUBLIC "-//Sun Microsystems Inc.//DTD JavaHelp TOC Version 1.0//EN"
         "http://java.sun.com/products/javahelp/toc_1_0.dtd">

<toc version="1.0">
  <tocitem image="toplevelfolder" target="Contenidos" text="Contenidos">
    <tocitem text="Controles">
      	<tocitem target="Control del teclado" text="Control del teclado"/>
    </tocitem>
    <tocitem text="Razas">
      	<tocitem target="Eleo" text="Eleo"/>
	<tocitem target="Ninfa" text="Ninfa"/>
	<tocitem target="Scraper" text="Scraper"/>
	<tocitem target="Biomorph" text="Biomorph"/>
	<tocitem target="GMarine" text="GMarine"/>
    </tocitem>
    <tocitem text="Escenarios">
      	<tocitem target="Eleuron" text="Eleuron"/>
	<tocitem target="OCB-5" text="OCB-5"/>
	<tocitem target="Silicosis" text="Silicosis"/>
	<tocitem target="Nodrubaz" text="Nodrubaz"/>
	<tocitem target="Campo de Asteroides" text="Campo de Asteroides"/>
    </tocitem>
  </tocitem>
</toc>